kdbxtool/__init__.py
kdbxtool/database.py
kdbxtool/exceptions.py
kdbxtool/merge.py
kdbxtool/py.typed
kdbxtool/templates.py
kdbxtool/models/__init__.py
kdbxtool/models/attachment.py
kdbxtool/models/entry.py
kdbxtool/models/group.py
kdbxtool/models/times.py
kdbxtool/parsing/__init__.py
kdbxtool/parsing/context.py
kdbxtool/parsing/header.py
kdbxtool/parsing/kdbx3.py
kdbxtool/parsing/kdbx4.py
kdbxtool/security/__init__.py
kdbxtool/security/crypto.py
kdbxtool/security/kdf.py
kdbxtool/security/keyfile.py
kdbxtool/security/memory.py
kdbxtool/security/totp.py
kdbxtool/security/yubikey.py
kdbxtool-0.1.7.dist-info/METADATA
kdbxtool-0.1.7.dist-info/WHEEL
kdbxtool-0.1.7.dist-info/licenses/LICENSE
kdbxtool-0.1.7.dist-info/RECORD
