Metadata-Version: 2.4
Name: kdbxtool
Version: 0.1.7
Summary: A modern, secure Python library for reading and writing KeePass KDBX databases
Project-URL: Homepage, https://github.com/coreyleavitt/kdbxtool
Project-URL: Documentation, https://coreyleavitt.github.io/kdbxtool/
Project-URL: Repository, https://github.com/coreyleavitt/kdbxtool
Author: Corey Leavitt
License-Expression: Apache-2.0
License-File: LICENSE
Keywords: encryption,kdbx,keepass,password,security
Classifier: Development Status :: 3 - Alpha
Classifier: Intended Audience :: Developers
Classifier: License :: OSI Approved :: Apache Software License
Classifier: Operating System :: OS Independent
Classifier: Programming Language :: Python :: 3
Classifier: Programming Language :: Python :: 3.12
Classifier: Programming Language :: Python :: 3.13
Classifier: Topic :: Security
Classifier: Topic :: Security :: Cryptography
Classifier: Typing :: Typed
Requires-Python: >=3.12
Requires-Dist: argon2-cffi>=23.1.0
Requires-Dist: defusedxml>=0.7.0
Requires-Dist: pycryptodomex>=3.20.0
Provides-Extra: twofish
Requires-Dist: oxifish>=0.1.1; extra == 'twofish'
Provides-Extra: yubikey
Requires-Dist: yubikey-manager>=5.0.0; extra == 'yubikey'
